MANIFEST.in
README.md
setup.py
countryware/__init__.py
countryware/admin.py
countryware/apps.py
countryware/country.json
countryware/country.py
countryware/defaults.py
countryware/fields.py
countryware/models.py
countryware/utils.py
countryware/__pycache__/__init__.cpython-36.pyc
countryware/__pycache__/admin.cpython-36.pyc
countryware/__pycache__/apps.cpython-36.pyc
countryware/__pycache__/country.cpython-36.pyc
countryware/__pycache__/defaults.cpython-36.pyc
countryware/__pycache__/models.cpython-36.pyc
countryware/locale/.DS_Store
countryware/locale/af/LC_MESSAGES/django.mo
countryware/locale/af/LC_MESSAGES/django.po
countryware/locale/am/LC_MESSAGES/django.mo
countryware/locale/am/LC_MESSAGES/django.po
countryware/locale/ar/LC_MESSAGES/django.mo
countryware/locale/ar/LC_MESSAGES/django.po
countryware/locale/as/LC_MESSAGES/django.mo
countryware/locale/as/LC_MESSAGES/django.po
countryware/locale/ast/LC_MESSAGES/django.mo
countryware/locale/ast/LC_MESSAGES/django.po
countryware/locale/az/LC_MESSAGES/django.mo
countryware/locale/az/LC_MESSAGES/django.po
countryware/locale/be/LC_MESSAGES/django.mo
countryware/locale/be/LC_MESSAGES/django.po
countryware/locale/bg/LC_MESSAGES/django.mo
countryware/locale/bg/LC_MESSAGES/django.po
countryware/locale/bn/LC_MESSAGES/django.mo
countryware/locale/bn/LC_MESSAGES/django.po
countryware/locale/bn_IN/LC_MESSAGES/django.mo
countryware/locale/bn_IN/LC_MESSAGES/django.po
countryware/locale/br/LC_MESSAGES/django.mo
countryware/locale/br/LC_MESSAGES/django.po
countryware/locale/bs/LC_MESSAGES/django.mo
countryware/locale/bs/LC_MESSAGES/django.po
countryware/locale/byn/LC_MESSAGES/django.mo
countryware/locale/byn/LC_MESSAGES/django.po
countryware/locale/ca/LC_MESSAGES/django.mo
countryware/locale/ca/LC_MESSAGES/django.po
countryware/locale/crh/LC_MESSAGES/django.mo
countryware/locale/crh/LC_MESSAGES/django.po
countryware/locale/cs/LC_MESSAGES/django.mo
countryware/locale/cs/LC_MESSAGES/django.po
django_countryware.egg-info/PKG-INFO
django_countryware.egg-info/SOURCES.txt
django_countryware.egg-info/dependency_links.txt
django_countryware.egg-info/requires.txt
django_countryware.egg-info/top_level.txt